{
    "chunks": [
        {
            "video_name": "Java in 100 Seconds",
            "text": "Java, a high-level multi-paradigm programming language famous for its ability to compile",
            "start": 0.0,
            "end": 5.12
        },
        {
            "video_name": "Java in 100 Seconds",
            "text": "to platform-independent bytecode.",
            "start": 5.12,
            "end": 7.42
        },
        {
            "video_name": "Java in 100 Seconds",
            "text": "It was designed by James Gosling in 1990 at Sun Microsystems.",
            "start": 7.42,
            "end": 11.68
        },
        {
            "video_name": "Java in 100 Seconds",
            "text": "One of its first demonstrations was the Star 7 PDA, which gave birth to the Java mascot,",
            "start": 11.68,
            "end": 16.84
        },
        {
            "video_name": "Java in 100 Seconds",
            "text": "Duke.",
            "start": 16.84,
            "end": 17.84
        },
        {
            "video_name": "Java in 100 Seconds",
            "text": "Today, it's one of the world's most popular programming languages.",
            "start": 17.84,
            "end": 20.24
        },
        {
            "video_name": "Java in 100 Seconds",
            "text": "It powers enterprise web apps with Spring Framework, big data pipelines with Hadoop,",
            "start": 20.24,
            "end": 24.28
        },
        {
            "video_name": "Java in 100 Seconds",
            "text": "mobile apps on Android, and even things like the controller for NASA's Maestro",
            "start": 24.28,
            "end": 28.44
        },
        {
            "video_name": "Java in 100 Seconds",
            "text": "Mars rover.",
            "start": 28.44,
            "end": 29.52
        },
        {
            "video_name": "Java in 100 Seconds",
            "text": "What made Java innovative is that instead of compiling to machine code, like C or C++,",
            "start": 29.52,
            "end": 34.58
        },
        {
            "video_name": "Java in 100 Seconds",
            "text": "it compiles to bytecode that can run on any operating system without recompiling, which",
            "start": 34.58,
            "end": 39.18
        },
        {
            "video_name": "Java in 100 Seconds",
            "text": "is made possible by executing the code with the Java Virtual Machine or JVM.",
            "start": 39.18,
            "end": 44.02
        },
        {
            "video_name": "Java in 100 Seconds",
            "text": "It's both a compiled and interpreted language at the same time.",
            "start": 44.02,
            "end": 47.14
        },
        {
            "video_name": "Java in 100 Seconds",
            "text": "The computer just needs to have the Java runtime environment, or JRE, installed, and most",
            "start": 47.14,
            "end": 51.9
        },
        {
            "video_name": "Java in 100 Seconds",
            "text": "of them do.",
            "start": 51.9,
            "end": 52.9
        },
        {
            "video_name": "Java in 100 Seconds",
            "text": "For developers, this means write once, run anywhere.",
            "start": 52.9,
            "end": 55.26
        },
        {
            "video_name": "Java in 100 Seconds",
            "text": "It's a strongly typed language with a curly brace syntax similar to the C family.",
            "start": 55.26,
            "end": 59.74
        },
        {
            "video_name": "Java in 100 Seconds",
            "text": "However, it provides more high level features like garbage collection,",
            "start": 59.74,
            "end": 63.42
        },
        {
            "video_name": "Java in 100 Seconds",
            "text": "runtime type checking, and reflection. To get started, install the Java development kit or",
            "start": 63.42,
            "end": 68.46
        },
        {
            "video_name": "Java in 100 Seconds",
            "text": "JDK, then create a file ending in .java. Every Java program starts with a class name,",
            "start": 68.46,
            "end": 73.82
        },
        {
            "video_name": "Java in 100 Seconds",
            "text": "which should also match the file name. The class is required to have a main method.",
            "start": 73.82,
            "end": 78.06
        },
        {
            "video_name": "Java in 100 Seconds",
            "text": "This is where your code will start executing. Inside the method define a variable by starting",
            "start": 78.06,
            "end": 82.7
        },
        {
            "video_name": "Java in 100 Seconds",
            "text": "with a type, followed by a name and value. We can then print it to the standard output",
            "start": 82.7,
            "end": 87.18
        },
        {
            "video_name": "Java in 100 Seconds",
            "text": "using the built-in system class. Now because we're inside of a class, we define functions as methods",
            "start": 87.18,
            "end": 92.54
        },
        {
            "video_name": "Java in 100 Seconds",
            "text": "on this class. The public keyword means that it can be used outside of this class, and static",
            "start": 92.54,
            "end": 97.26
        },
        {
            "video_name": "Java in 100 Seconds",
            "text": "means that it's a member of the class itself, as opposed to an instance of the class. We then",
            "start": 97.26,
            "end": 101.74
        },
        {
            "video_name": "Java in 100 Seconds",
            "text": "provide a type and name, and return a value from it. You can define your own custom classes,",
            "start": 101.74,
            "end": 106.54
        },
        {
            "video_name": "Java in 100 Seconds",
            "text": "which are blueprints for objects, then add attributes and methods to them. Use the",
            "start": 106.54,
            "end": 110.86
        },
        {
            "video_name": "Java in 100 Seconds",
            "text": "new keyword to instantiate an object from the class. It feels very object-oriented, but has evolved to",
            "start": 110.86,
            "end": 116.38
        },
        {
            "video_name": "Java in 100 Seconds",
            "text": "support functional patterns like anonymous lambda methods. When your program is finished, use the",
            "start": 116.38,
            "end": 120.86
        },
        {
            "video_name": "Java in 100 Seconds",
            "text": "compiler to generate a .class file, which contains the bytecode. Now use the java command to tell the",
            "start": 120.86,
            "end": 126.7
        },
        {
            "video_name": "Java in 100 Seconds",
            "text": "jvm to interpret and run that file. Congratulations, you just built an enterprise-grade application.",
            "start": 126.7,
            "end": 132.46
        },
        {
            "video_name": "Java in 100 Seconds",
            "text": "This has been Java in 100 seconds. Hit subscribe for more short videos like this,",
            "start": 132.46,
            "end": 136.78
        },
        {
            "video_name": "Java in 100 Seconds",
            "text": "and if we somehow get to 100,000 likes on this video, I'll do a full Java tutorial.",
            "start": 136.78,
            "end": 141.26
        },
        {
            "video_name": "Java in 100 Seconds",
            "text": "Thanks for watching, and I will see you in the next one.",
            "start": 141.26,
            "end": 144.3
        }
    ],
    "full_text": "Java, a high-level multi-paradigm programming language famous for its ability to compile to platform-independent bytecode. It was designed by James Gosling in 1990 at Sun Microsystems. One of its first demonstrations was the Star 7 PDA, which gave birth to the Java mascot, Duke. Today, it's one of the world's most popular programming languages. It powers enterprise web apps with Spring Framework, big data pipelines with Hadoop, mobile apps on Android, and even things like the controller for NASA's Maestro Mars rover. What made Java innovative is that instead of compiling to machine code, like C or C++, it compiles to bytecode that can run on any operating system without recompiling, which is made possible by executing the code with the Java Virtual Machine or JVM. It's both a compiled and interpreted language at the same time. The computer just needs to have the Java runtime environment, or JRE, installed, and most of them do. For developers, this means write once, run anywhere. It's a strongly typed language with a curly brace syntax similar to the C family. However, it provides more high level features like garbage collection, runtime type checking, and reflection. To get started, install the Java development kit or JDK, then create a file ending in .java. Every Java program starts with a class name, which should also match the file name. The class is required to have a main method. This is where your code will start executing. Inside the method define a variable by starting with a type, followed by a name and value. We can then print it to the standard output using the built-in system class. Now because we're inside of a class, we define functions as methods on this class. The public keyword means that it can be used outside of this class, and static means that it's a member of the class itself, as opposed to an instance of the class. We then provide a type and name, and return a value from it. You can define your own custom classes, which are blueprints for objects, then add attributes and methods to them. Use the new keyword to instantiate an object from the class. It feels very object-oriented, but has evolved to support functional patterns like anonymous lambda methods. When your program is finished, use the compiler to generate a .class file, which contains the bytecode. Now use the java command to tell the jvm to interpret and run that file. Congratulations, you just built an enterprise-grade application. This has been Java in 100 seconds. Hit subscribe for more short videos like this, and if we somehow get to 100,000 likes on this video, I'll do a full Java tutorial. Thanks for watching, and I will see you in the next one."
}